tfli2c/__init__.py
tfli2c/docs/__init__.py
tfli2c/tests/__init__.py
tfli2c/tests/tfli2c_simple.py
tfli2c/tests/tfli2c_test.py
tfli2c-0.0.1.dist-info/LICENSE
tfli2c-0.0.1.dist-info/METADATA
tfli2c-0.0.1.dist-info/WHEEL
tfli2c-0.0.1.dist-info/top_level.txt
tfli2c-0.0.1.dist-info/RECORD
