Metadata-Version: 2.1
Name: tfli2c
Version: 0.0.1
Summary: Added address parameter interpretation
Home-page: https://github.com/budryerson/TFLuna-I2C_python
Author: Bud Ryerson
Author-email: bud@budryerson.com
License: UNKNOWN
Project-URL: Bug Tracker, https://github.com/budryerson/TFLuna-I2C_python/issues
Platform: UNKNOWN
Classifier: Programming Language :: Python :: 3
Classifier: License :: OSI Approved :: MIT License
Classifier: Operating System :: OS Independent
Requires-Python: >=3.6
License-File: LICENSE
Requires-Dist: smbus
